<lib>
  <bitmapdata class="10000_3_6_0000" index="0" x="-17" y="-80" file="E:\FlashObject\assect\GameEditor\cfg\action\actionImages\10000\3\6\0000.png" compression="false" quality="100"/>
  <bitmapdata class="10000_3_6_0001" index="1" x="-24" y="-81" file="E:\FlashObject\assect\GameEditor\cfg\action\actionImages\10000\3\6\0001.png" compression="false" quality="100"/>
  <bitmapdata class="10000_3_6_0002" index="2" x="-28" y="-82" file="E:\FlashObject\assect\GameEditor\cfg\action\actionImages\10000\3\6\0002.png" compression="false" quality="100"/>
  <bitmapdata class="10000_3_6_0003" index="3" x="-28" y="-82" file="E:\FlashObject\assect\GameEditor\cfg\action\actionImages\10000\3\6\0003.png" compression="false" quality="100"/>
  <bitmapdata class="10000_3_6_0004" index="4" x="-27" y="-82" file="E:\FlashObject\assect\GameEditor\cfg\action\actionImages\10000\3\6\0004.png" compression="false" quality="100"/>
  <bitmapdata class="10000_3_6_0005" index="5" x="-26" y="-80" file="E:\FlashObject\assect\GameEditor\cfg\action\actionImages\10000\3\6\0005.png" compression="false" quality="100"/>
  <bitmapdata class="10000_3_6_0006" index="6" x="-26" y="-79" file="E:\FlashObject\assect\GameEditor\cfg\action\actionImages\10000\3\6\0006.png" compression="false" quality="100"/>
  <bitmapdata class="10000_3_6_0007" index="7" x="-26" y="-78" file="E:\FlashObject\assect\GameEditor\cfg\action\actionImages\10000\3\6\0007.png" compression="false" quality="100"/>
  <bitmapdata class="10000_3_6_0008" index="8" x="-24" y="-79" file="E:\FlashObject\assect\GameEditor\cfg\action\actionImages\10000\3\6\0008.png" compression="false" quality="100"/>
  <bitmapdata class="10000_3_6_0009" index="9" x="-20" y="-81" file="E:\FlashObject\assect\GameEditor\cfg\action\actionImages\10000\3\6\0009.png" compression="false" quality="100"/>
  <bitmapdata class="10000_3_6_0010" index="10" x="-20" y="-83" file="E:\FlashObject\assect\GameEditor\cfg\action\actionImages\10000\3\6\0010.png" compression="false" quality="100"/>
  <bitmapdata class="10000_3_6_0011" index="11" x="-21" y="-83" file="E:\FlashObject\assect\GameEditor\cfg\action\actionImages\10000\3\6\0011.png" compression="false" quality="100"/>
  <bitmapdata class="10000_3_6_0012" index="12" x="-25" y="-83" file="E:\FlashObject\assect\GameEditor\cfg\action\actionImages\10000\3\6\0012.png" compression="false" quality="100"/>
  <bitmapdata class="10000_3_6_0013" index="13" x="-27" y="-81" file="E:\FlashObject\assect\GameEditor\cfg\action\actionImages\10000\3\6\0013.png" compression="false" quality="100"/>
  <bitmapdata class="10000_3_6_0014" index="14" x="-25" y="-80" file="E:\FlashObject\assect\GameEditor\cfg\action\actionImages\10000\3\6\0014.png" compression="false" quality="100"/>
  <bitmapdata class="10000_3_6_0015" index="15" x="-19" y="-79" file="E:\FlashObject\assect\GameEditor\cfg\action\actionImages\10000\3\6\0015.png" compression="false" quality="100"/>
</lib>